README.md
setup.py
remoteobj/__init__.py
remoteobj/base.py
remoteobj/core.py
remoteobj/excs.py
remoteobj/util.py
remoteobj/view.py
remoteobj.egg-info/PKG-INFO
remoteobj.egg-info/SOURCES.txt
remoteobj.egg-info/dependency_links.txt
remoteobj.egg-info/requires.txt
remoteobj.egg-info/top_level.txt