Metadata-Version: 2.1
Name: remoteobj
Version: 0.4.0
Summary: Facilitating cross-process programming.
Home-page: https://github.com/beasteers/remoteobj
Author: Bea Steers
Author-email: bea.steers@gmail.com
License: MIT License
Keywords: multiprocessing process except raise exception handling proxy remote ops result yield
Platform: UNKNOWN
